Workbook

Sheet Start
B2: Tsumiki – Datenbank
B3: Diese Datei ist die Datenbank des Systems. Die Website schreibt jede Bestellung sofort hier hinein.
B4: Wichtig: Datei nicht geöffnet lassen, während Bestellungen laufen – Excel sperrt sie sonst (das System legt dann eine Sicherungskopie an).
B6: Blätter
B7: Parameter – alle Preise, Gebühren, Kurse und Regeln. Nur Spalte "Wert" ändern.
B8: Kalkulator – Endpreis für einen Artikel ausrechnen, ohne die Website zu öffnen.
B9: Bestellungen / Positionen – jede Kundenbestellung und jeder einzelne Artikel.
B10: Sammelsendungen – jede Kiste aus Japan mit kalkulierten und tatsächlichen Kosten.
B11: Rechnungen – fortlaufend nummeriert, nie ändern oder löschen (GoBD). Korrektur nur per Gutschrift.
B12: Journal – alle Buchungen (Kontenvorschlag SKR03, mit Steuerberaterin abstimmen).
B13: Postausgang – jede E-Mail, die an Kunden ging.
B14: Protokoll – wer hat wann was gemacht.
B15: Auswertung – Kennzahlen auf einen Blick.

Sheet Parameter
A1: Schlüssel | B1: Wert | C1: Einheit | D1: Beschreibung
A2: marke_name | B2: Tsumiki | D2: Markenname auf Website, Mails und Rechnungen
A3: firma_inhaber | B3: Bastian Karlshaus | D3: Unternehmer (Einzelunternehmen)
A4: firma_strasse | B4: [Straße Hausnummer] | D4: Anschrift für Impressum und Rechnung
A5: firma_plz_ort | B5: [PLZ] Wuppertal
A6: firma_email | B6: hallo@[domain].de | D6: Kontakt-E-Mail
A7: firma_ustid | B7: [USt-IdNr. folgt] | D7: USt-IdNr. oder Steuernummer für Rechnungen
A8: firma_iban | B8: DE00 0000 0000 0000 0000 00 | D8: Bankverbindung für Überweisung (Platzhalter)
A9: kurs_jpy_je_eur_fallback | B9: 185 | C9: JPY/EUR | D9: Fallback-Kurs, falls der Tageskurs nicht abrufbar ist
A10: kurs_puffer | B10: 0.02 | C10: % | D10: Sicherheitsabschlag auf den Tageskurs (Wise-Gebühr + Schwankung bis zum Kauf)
A11: sendico_gebuehr_jpy | B11: 500 | C11: JPY | D11: Sendico-Servicegebühr je Kauf
A12: sendico_aufschlag_marktplatz_jpy | B12: 300 | C12: JPY | D12: Zusatz bei Mercari und Yahoo Auctions (seit 01.08.2026)
A13: inlandsversand_japan_schaetzung_jpy | B13: 750 | C13: JPY | D13: Schätzung, wenn der Inlandsversand nicht im Preis enthalten ist
A14: fracht_eur_je_kg | B14: 10 | C14: EUR/kg | D14: Kurier-Economy Japan → DE (Schätzung aus Tarifen)
A15: sendung_fixkosten_eur | B15: 45 | C15: EUR | D15: Grundpreis Fracht + Verzollungsgebühr je Sammelsendung (RD-Ist: 15–89 € Gebühren)
A16: sendung_erwartete_positionen | B16: 30 | C16: Stück | D16: Auf so viele Positionen werden die Fixkosten verteilt
A17: zoll_satz_karten | B17: 0.027 | C17: % | D17: Zollsatz 9504 40 00 (Spielkarten), ohne Ursprungsnachweis
A18: mindestmenge_sendung | B18: 10 | C18: Aufträge | D18: Sammelsendung geht ab dieser Anzahl Aufträge raus
A19: stichtag_tag | B19: 20 | C19: Tag | D19: Monatlicher Stichtag für die Sammelsendung
A20: laufzeit_tage_min | B20: 10 | C20: Tage | D20: Lieferzeit ab Stichtag bis zum Kunden (min)
A21: laufzeit_tage_max | B21: 16 | C21: Tage | D21: Lieferzeit ab Stichtag bis zum Kunden (max)
A22: gewicht_einzelkarte_kg | B22: 0.04 | C22: kg
A23: gewicht_slab_kg | B23: 0.13 | C23: kg | D23: Gegradete Karte (PSA/BGS/CGC)
A24: gewicht_booster_kg | B24: 0.05 | C24: kg | D24: Booster / einzelne Packs
A25: gewicht_display_kg | B25: 0.45 | C25: kg | D25: Display / Box (versiegelt)
A26: gewicht_sonstiges_kg | B26: 0.25 | C26: kg | D26: Deck, Promo-Set, Zubehör
A27: gebuehr_grund_eur | B27: 5 | C27: EUR | D27: Servicegebühr fix je Bestellung
A28: gebuehr_prozent | B28: 0.05 | C28: % | D28: Servicegebühr auf den Warenwert (1–2 Artikel)
A29: gebuehr_prozent_ab3 | B29: 0.045 | C29: % | D29: Mengenrabatt ab 3 Artikeln
A30: gebuehr_prozent_ab6 | B30: 0.04 | C30: % | D30: Mengenrabatt ab 6 Artikeln
A31: gebuehr_max_eur | B31: 40 | C31: EUR | D31: Deckel für die Servicegebühr je Bestellung
A32: warenwert_min_eur | B32: 5 | C32: EUR | D32: Mindestwert je Artikel
A33: warenwert_max_eur | B33: 300 | C33: EUR | D33: Höchstwert je Artikel (Versandrisiko!)
A34: versand_de_grenze_eur | B34: 50 | C34: EUR | D34: Bis zu diesem Warenwert günstiger Versand
... A41: allein_kurier_grund_eur | B41: 22 | C41: EUR | D41: Kurier Japan → Haustür, Grundpreis kleines Paket
A42: allein_kurier_eur_je_kg | B42: 9 | C42: EUR/kg
A43: allein_pauschalzoll_eur | B43: 3 | C43: EUR | D43: Pauschalzoll je Warenkategorie bis 150 € (seit 01.07.2026)
A44: allein_verzollungsgebuehr_eur | B44: 15 | C44: EUR | D44: Gebühr des Kuriers für die Verzollung (DHL Express min. 14,88 €)
A45: zahlung_prozent | B45: 0.0249 | C45: % | D45: Zahlungsgebühr variabel (PayPal/Stripe, Schätzung)
A46: zahlung_fix_eur | B46: 0.35 | C46: EUR | D46: Zahlungsgebühr fix je Zahlung

Sheet Kalkulator
A1: Endpreis-Kalkulator (ein Artikel, Lieferung nach Deutschland)
A2: Gelbe Felder ausfüllen. Ergebnis entspricht dem Preis auf der Website.
E3: Artikelart → Gewicht (kg)
A4: Preis in Japan (¥) | B4: 9250 | E4: Einzelkarte | F4: =VLOOKUP("gewicht_einzelkarte_kg",Parameter!$A:$B,2,FALSE)
A5: Artikelart | B5: Einzelkarte | E5: Gegradete Karte | F5: =VLOOKUP("gewicht_slab_kg",Parameter!$A:$B,2,FALSE)
A6: Inlandsversand im Preis enthalten? (ja/nein) | B6: ja | E6: Booster / Packs | F6: =VLOOKUP("gewicht_booster_kg",Parameter!$A:$B,2,FALSE)
A7: Mercari oder Yahoo? (ja/nein) | B7: ja | E7: Display / Box | F7: =VLOOKUP("gewicht_display_kg",Parameter!$A:$B,2,FALSE)
A8: Anzahl Artikel in der Bestellung (für Rabatt) | B8: 1 | E8: Deck, Promo-Set, Zubehör | F8: =VLOOKUP("gewicht_sonstiges_kg",Parameter!$A:$B,2,FALSE)
A9: Tageskurs ¥ je € (EZB) | B9: =VLOOKUP("kurs_jpy_je_eur_fallback",Parameter!$A:$B,2,FALSE)
A11: Effektiver Kurs (mit Puffer) | B11: =B9*(1-VLOOKUP("kurs_puffer",Parameter!$A:$B,2,FALSE))
A12: Warenwert (€) | B12: =ROUND(B4/B11,2)
A13: Inlandsversand Japan (€) | B13: =IF(B6="nein",ROUND(VLOOKUP("inlandsversand_japan_schaetzung_jpy",Parameter!$A:$B,2,FALSE)/B11,2),0)
A14: Sendico-Gebühr (€) | B14: =ROUND((VLOOKUP("sendico_gebuehr_jpy",Parameter!$A:$B,2,FALSE)+IF(B7="ja",VLOOKUP("sendico_aufschlag_marktplatz_jpy",Parameter!$A:$B,2,FALSE),0))/B11,2)
A15: Gewicht (kg) | B15: =VLOOKUP(B5,$E$4:$F$8,2,FALSE)
A16: Fracht + Anteil Fixkosten (€) | B16: =ROUND(B15*VLOOKUP("fracht_eur_je_kg",Parameter!$A:$B,2,FALSE),2)+ROUND(VLOOKUP("sendung_fixkosten_eur",Parameter!$A:$B,2,FALSE)/VLOOKUP("sendung_erwartete_positionen",Parameter!$A:$B,2,FALSE),2)
A17: Zoll (€) | B17: =ROUND((B12+B13+ROUND(B15*VLOOKUP("fracht_eur_je_kg",Parameter!$A:$B,2,FALSE),2))*VLOOKUP("zoll_satz_karten",Parameter!$A:$B,2,FALSE),2)
A18: Servicegebühr (€) | B18: =ROUND(MIN(VLOOKUP("gebuehr_grund_eur",Parameter!$A:$B,2,FALSE)+B12*IF(B8>=6,VLOOKUP("gebuehr_prozent_ab6",Parameter!$A:$B,2,FALSE),IF(B8>=3,VLOOKUP("gebuehr_prozent_ab3",Parameter!$A:$B,2,FALSE),VLOOKUP("gebuehr_prozent",Parameter!$A:$B,2,FALSE))),VLOOKUP("gebuehr_max_eur",Parameter!$A:$B,2,FALSE)),2)
A19: Versand zum Kunden (€) | B19: =IF(B12<=VLOOKUP("versand_de_grenze_eur",Parameter!$A:$B,2,FALSE),VLOOKUP("versand_de_klein_eur",Parameter!$A:$B,2,FALSE),VLOOKUP("versand_de_paket_eur",Parameter!$A:$B,2,FALSE))
A20: Summe netto (€) | B20: =SUM(B12:B14)+SUM(B16:B19)
A21: Umsatzsteuer (€) | B21: =ROUND(B20*VLOOKUP("ust_satz_de",Parameter!$A:$B,2,FALSE),2)
A22: ENDPREIS für den Kunden (€) | B22: =B20+B21
A24: Vergleich: Kunde bestellt allein (€) | B24: =ROUND(B12+B13+B14+(VLOOKUP("allein_kurier_grund_eur",Parameter!$A:$B,2,FALSE)+MAX(0.5,B15)*VLOOKUP("allein_kurier_eur_je_kg",Parameter!$A:$B,2,FALSE))+IF(B12+B13+VLOOKUP("allein_kurier_grund_eur",Parameter!$A:$B,2,FALSE)+MAX(0.5,B15)*VLOOKUP("allein_kurier_eur_je_kg",Parameter!$A:$B,2,FALSE)<=150,VLOOKUP("allein_pauschalzoll_eur",Parameter!$A:$B,2,FALSE),(B12+B13+VLOOKUP("allein_kurier_grund_eur",Parameter!$A:$B,2,FALSE)+MAX(0.5,B15)*VLOOKUP("allein_kurier_eur_je_kg",Parameter!$A:$B,2,FALSE))*VLOOKUP("zoll_satz_karten",Parameter!$A:$B,2,FALSE))+(B12+B13+VLOOKUP("allein_kurier_grund_eur",Parameter!$A:$B,2,FALSE)+MAX(0.5,B15)*VLOOKUP("allein_kurier_eur_je_kg",Parameter!$A:$B,2,FALSE)+IF(B12+B13+VLOOKUP("allein_kurier_grund_eur",Parameter!$A:$B,2,FALSE)+MAX(0.5,B15)*VLOOKUP("allein_kurier_eur_je_kg",Parameter!$A:$B,2,FALSE)<=150,VLOOKUP("allein_pauschalzoll_eur",Parameter!$A:$B,2,FALSE),(B12+B13+VLOOKUP("allein_kurier_grund_eur",Parameter!$A:$B,2,FALSE)+MAX(0.5,B15)*VLOOKUP("allein_kurier_eur_je_kg",Parameter!$A:$B,2,FALSE))*VLOOKUP("zoll_satz_karten",Parameter!$A:$B,2,FALSE)))*VLOOKUP("ust_satz_de",Parameter!$A:$B,2,FALSE)+MAX(VLOOKUP("allein_verzollungsgebuehr_eur",Parameter!$A:$B,2,FALSE),0.02*(B12+B13+VLOOKUP("allein_kurier_grund_eur",Parameter!$A:$B,2,FALSE)+MAX(0.5,B15)*VLOOKUP("allein_kurier_eur_je_kg",Parameter!$A:$B,2,FALSE))),2)
A25: Ersparnis für den Kunden (€) | B25: =B24-B22
A26: Dein Gewinn (Gebühr − Zahlungsgebühr) (€) | B26: =ROUND(B18-(B22*VLOOKUP("zahlung_prozent",Parameter!$A:$B,2,FALSE)+VLOOKUP("zahlung_fix_eur",Parameter!$A:$B,2,FALSE)),2)

Sheet Bestellungen
A1: BE_Nr | B1: BE_Token | C1: BE_Datum | D1: BE_Status | E1: BE_Name | F1: BE_Email | G1: BE_Strasse | H1: BE_PLZ | I1: BE_Ort | J1: BE_Land | K1: BE_Zahlart | L1: BE_Zahlstatus | M1: BE_Zahlungsref | N1: BE_Betrag_reserviert | O1: BE_Betrag_abgebucht | P1: BE_Warenwert | Q1: BE_Importkosten_kalk | R1: BE_Servicegebuehr | S1: BE_Versand | T1: BE_Netto | U1: BE_USt_Satz | V1: BE_USt | W1: BE_Brutto | X1: BE_Vergleich_allein | Y1: BE_Kurs_JPY | Z1: BE_Sendung | AA1: BE_Rechnung | AB1: BE_Versanddatum | AC1: BE_Tracking | AD1: BE_Notiz
A2: T-2026-0001 | B2: y4ertga730uyvix4 | C2: 46272.302 | D2: versendet | E2: Lena Hoffmann | F2: lena@example.de | G2: Musterstraße 1 | H2: 50667 | I2: Köln | J2: DE | K2: paypal | L2: abgebucht | M2: DEMO-T-2026-0001 | N2: 123.45 | O2: 123.45 | P2: 74.19 | Q2: 14.65 | R2: 8.71 | S2: 6.19 | T2: 103.74 | U2: 0.19 | V2: 19.71 | W2: 123.45 | X2: 147.21 | Y2: 181.3 | Z2: S-2026-09-1 | AA2: RE-2026-0001 | AB2: 46289.552 | AC2: 003404342460298630
A3: T-2026-0002 | B3: v3wzgijaoivp7mnb | C3: 46274.302 | D3: versendet | E3: Jonas Becker | F3: jonas@example.de | G3: Musterstraße 1 | H3: 42103 | I3: Wuppertal | J3: DE | K3: stripe | L3: abgebucht | M3: DEMO-T-2026-0002 | N3: 211.39 | O3: 211.39 | P3: 147.82 | Q3: 11.24 | R3: 12.39 | S3: 6.19 | T3: 177.64 | U3: 0.19 | V3: 33.75 | W3: 211.39 | X3: 232.45 | Y3: 181.3 | Z3: S-2026-09-1 | AA3: RE-2026-0002 | AB3: 46289.552 | AC3: 003404347721327561
A4: T-2026-0003 | B4: ncs9rl8kdnmubgr1 | C4: 46276.302 | D4: versendet | E4: Mia Wagner | F4: mia@example.de | G4: Musterstraße 1 | H4: 1010 | I4: Wien | J4: AT | K4: ueberweisung | L4: bezahlt | N4: 0 | O4: 107.65 | P4: 51.3 | Q4: 16.69 | R4: 7.57 | S4: 14.9 | T4: 90.46 | U4: 0.19 | V4: 17.19 | W4: 107.65 | X4: 118.32 | Y4: 181.3 | Z4: S-2026-09-1 | AA4: RE-2026-0003 | AB4: 46289.552 | AC4: 003404342558005126
A5: T-2026-0004 | B5: e0n1di8agv9gy13z | C5: 46303.302 | D5: gekauft | E5: Tim Schulz | F5: tim@example.de | G5: Musterstraße 1 | H5: 40210 | I5: Düsseldorf | J5: DE | K5: paypal | L5: abgebucht | M5: DEMO-T-2026-0004 | N5: 191.39 | O5: 164.79 | P5: 106.46 | Q5: 15.51 | R5: 10.32 | S5: 6.19 | T5: 138.48 | U5: 0.19 | V5: 26.31 | W5: 164.79 | X5: 185.61 | Y5: 181.3
A6: T-2026-0005 | B6: 79dtwjhbzn3cvmk2 | C6: 46307.302 | D6: gekauft | E6: Sara Klein | F6: sara@example.de | G6: Musterstraße 1 | H6: 45127 | I6: Essen | J6: DE | K6: stripe | L6: abgebucht | M6: DEMO-T-2026-0005 | N6: 67.93 | O6: 67.93 | P6: 40.82 | Q6: 7.42 | R6: 7.04 | S6: 1.8 | T6: 57.08 | U6: 0.19 | V6: 10.85 | W6: 67.93 | X6: 103.09 | Y6: 181.3
A7: T-2026-0006 | B7: t5ezyohtuy035kzw | C7: 46312.302 | D7: neu | E7: Paul Neumann | F7: paul@example.de | G7: Musterstraße 1 | H7: 44787 | I7: Bochum | J7: DE | K7: paypal | L7: reserviert | M7: DEMO-T-2026-0006 | N7: 119.4 | O7: 0 | P7: 71.71 | Q7: 13.85 | R7: 8.59 | S7: 6.19 | T7: 100.34 | U7: 0.19 | V7: 19.06 | W7: 119.4 | X7: 142.61 | Y7: 181.3

Sheet Positionen
A1: POS_Nr | B1: POS_Bestellung | C1: POS_Status | D1: POS_Link | E1: POS_Plattform | F1: POS_Titel | G1: POS_Art | H1: POS_Menge | I1: POS_Preis_JPY | J1: POS_Inland_JPY | K1: POS_Sendico_JPY | L1: POS_Gewicht_kg | M1: POS_Ware_EUR_kalk | N1: POS_Import_EUR_kalk | O1: POS_Zoll_EUR_kalk | P1: POS_Fracht_EUR_kalk | Q1: POS_Netto_EUR | R1: POS_Brutto_EUR | S1: POS_Sendico_Nr | T1: POS_Kaufdatum | U1: POS_Ist_Preis_JPY | V1: POS_Ist_Kurs | W1: POS_Ist_Ware_EUR | X1: POS_Ist_Sendico_EUR | Y1: POS_Ist_Logistik_EUR | Z1: POS_Sendung | AA1: POS_Geprueft
A2: T-2026-0001-1 | B2: T-2026-0001 | C2: versendet | D2: https://jp.mercari.com/item/m81234567011 | E2: mercari | F2: Pikachu Promo (japanisch) | G2: einzelkarte | H2: 1 | I2: 9250 | J2: 0 | K2: 800 | L2: 0.04 | M2: 51.02 | N2: 7.7 | O2: 1.39 | P2: 1.9 | Q2: 68.97 | R2: 82.07 | S2: Z-165243 | T2: 46273.76 | U2: 9250 | V2: 185 | W2: 50 | X2: 4.32 | Y2: 2.57 | Z2: S-2026-09-1 | AA2: ja
A3: T-2026-0001-2 | B3: T-2026-0001 | C3: versendet | D3: https://jp.mercari.com/item/m81234567012 | E3: mercari | F3: Evoli Illustration Rare | G3: einzelkarte | H3: 1 | I3: 4200 | J3: 0 | K3: 800 | L3: 0.04 | M3: 23.17 | N3: 6.95 | O3: 0.64 | P3: 1.9 | Q3: 34.77 | R3: 41.38 | S3: Z-162253 | T3: 46273.76 | U3: 4200 | V3: 185 | W3: 22.7 | X3: 4.32 | Y3: 2.57 | Z3: S-2026-09-1 | AA3: ja
A4: T-2026-0002-1 | B4: T-2026-0002 | C4: versendet | D4: https://page.auctions.yahoo.co.jp/jp/auction/x123456789 | E4: yahoo | F4: PSA 10 Gengar (japanisch) | G4: slab | H4: 1 | I4: 26800 | J4: 0 | K4: 800 | L4: 0.13 | M4: 147.82 | N4: 11.24 | O4: 4.03 | P4: 2.8 | Q4: 177.64 | R4: 211.39 | S4: Z-160889 | T4: 46275.76 | U4: 26800 | V4: 185 | W4: 144.86 | X4: 4.32 | Y4: 8.35 | Z4: S-2026-09-1 | AA4: ja
A5: T-2026-0003-1 | B5: T-2026-0003 | C5: versendet | D5: https://www.suruga-ya.jp/product/detail/602000001 | E5: surugaya | F5: One Piece Card Game Booster Display | G5: display | H5: 1 | I5: 6900 | J5: 0 | K5: 500 | L5: 0.45 | M5: 38.06 | N5: 9.91 | O5: 1.15 | P5: 6 | Q5: 64.64 | R5: 76.92 | S5: Z-160404 | T5: 46277.76 | U5: 6900 | V5: 185 | W5: 37.3 | X5: 2.7 | Y5: 28.9 | Z5: S-2026-09-1 | AA5: ja
A6: T-2026-0003-2 | B6: T-2026-0003 | C6: versendet | D6: https://jp.mercari.com/item/m81234567031 | E6: mercari | F6: Yu-Gi-Oh! OCG Booster (3 Packs) | G6: booster | H6: 1 | I6: 2400 | J6: 0 | K6: 800 | L6: 0.05 | M6: 13.24 | N6: 6.78 | O6: 0.37 | P6: 2 | Q6: 25.82 | R6: 30.73 | S6: Z-162161 | T6: 46277.76 | U6: 2400 | V6: 185 | W6: 12.97 | X6: 4.32 | Y6: 3.2 | Z6: S-2026-09-1 | AA6: ja
A7: T-2026-0004-1 | B7: T-2026-0004 | C7: gekauft | D7: https://jp.mercari.com/item/m81234567041 | E7: mercari | F7: Glurak SAR (japanisch) | G7: einzelkarte | H7: 1 | I7: 15800 | J7: 0 | K7: 800 | L7: 0.04 | M7: 87.15 | N7: 8.67 | O7: 2.36 | P7: 1.9 | Q7: 109.34 | R7: 130.11 | S7: Z-165893 | T7: 46304.76 | U7: 15800 | V7: 185 | W7: 85.41 | X7: 4.32
A8: T-2026-0004-2 | B8: T-2026-0004 | C8: gekauft | D8: https://jp.mercari.com/item/m81234567042 | E8: mercari | F8: Mew Promo (japanisch) | G8: einzelkarte | H8: 1 | I8: 3500 | J8: 0 | K8: 800 | L8: 0.04 | M8: 19.31 | N8: 6.84 | O8: 0.53 | P8: 1.9 | Q8: 29.14 | R8: 34.68 | S8: Z-161163 | T8: 46304.76 | U8: 3500 | V8: 185 | W8: 18.92 | X8: 4.32
A9: T-2026-0004-3 | B9: T-2026-0004 | C9: nicht_verfuegbar | D9: https://jp.mercari.com/item/m81234567043 | E9: mercari | F9: Relaxo Art Rare | G9: einzelkarte | H9: 1 | I9: 2800 | J9: 0 | K9: 800 | L9: 0.04 | M9: 15.44 | N9: 6.74 | O9: 0.43 | P9: 1.9 | Q9: 24.29 | R9: 28.91
A10: T-2026-0005-1 | B10: T-2026-0005 | C10: gekauft | D10: https://jp.mercari.com/item/m81234567051 | E10: mercari | F10: Nachtara Alt Art (japanisch) | G10: einzelkarte | H10: 1 | I10: 7400 | J10: 0 | K10: 800 | L10: 0.04 | M10: 40.82 | N10: 7.42 | O10: 1.11 | P10: 1.9 | Q10: 57.08 | R10: 67.93 | S10: Z-160845 | T10: 46308.76 | U10: 7400 | V10: 185 | W10: 40 | X10: 4.32
A11: T-2026-0006-1 | B11: T-2026-0006 | C11: angefragt | D11: https://jp.mercari.com/item/m81234567061 | E11: mercari | F11: PSA 10 Bisasam (japanisch) | G11: slab | H11: 1 | I11: 11200 | J11: 0 | K11: 800 | L11: 0.13 | M11: 61.78 | N11: 8.91 | O11: 1.7 | P11: 2.8 | Q11: 83.42 | R11: 99.27
A12: T-2026-0006-2 | B12: T-2026-0006 | C12: angefragt | D12: https://item.fril.jp/abc123 | E12: rakuma | F12: Digimon Card Game Promo | G12: einzelkarte | H12: 1 | I12: 1800 | J12: 0 | K12: 500 | L12: 0.04 | M12: 9.93 | N12: 4.94 | O12: 0.28 | P12: 1.9 | Q12: 16.92 | R12: 20.13

Sheet Sammelsendungen
A1: SE_Nr | B1: SE_Status | C1: SE_Erstellt | D1: SE_Kurier | E1: SE_Tracking | F1: SE_Gewicht_kg | G1: SE_Fracht_JPY | H1: SE_Fracht_EUR | I1: SE_Zoll_EUR | J1: SE_EUSt_EUR | K1: SE_Verzollung_EUR | L1: SE_Sonstiges_EUR | M1: SE_Positionen | N1: SE_Auftraege | O1: SE_Warenwert_EUR | P1: SE_Logistik_kalk_EUR | Q1: SE_Logistik_ist_EUR | R1: SE_Abweichung_EUR | S1: SE_Versendet | T1: SE_Angekommen
A2: S-2026-09-1 | B2: angekommen | C2: 46282.26 | D2: FedEx Economy (Sendico) | E2: 7712 3456 0001 | F2: 1.2 | G2: 4900 | H2: 26.49 | I2: 4.1 | J2: 63.4 | K2: 15 | L2: 0 | M2: 5 | N2: 3 | O2: 267.83 | P2: 22.18 | Q2: 45.59 | R2: -23.41 | S2: 46282.302 | T2: 46288.385

Sheet Rechnungen
A1: RE_Nr | B1: RE_Datum | C1: RE_Leistungsdatum | D1: RE_Bestellung | E1: RE_Typ | F1: RE_Bezug | G1: RE_Kunde | H1: RE_Land | I1: RE_Netto | J1: RE_USt_Satz | K1: RE_USt | L1: RE_Brutto | M1: RE_Positionen
A2: RE-2026-0001 | B2: 46289.552 | C2: 46289.552 | D2: T-2026-0001 | E2: Rechnung | G2: Lena Hoffmann | H2: DE | I2: 103.74 | J2: 0.19 | K2: 19.71 | L2: 123.45 | M2: [{"text":"Pikachu Promo (japanisch) (mercari, 1 Stk.)","sub":"Beschaffung in Japan inkl. Import · Sendico-Nr. Z-165243","net":68.97},{"text":"Evoli Illustration Rare (mercari, 1 Stk.)","sub":"Beschaffung in Japan inkl. Import · Sendico-Nr. Z-162253","net":34.77}]
A3: RE-2026-0002 | B3: 46289.552 | C3: 46289.552 | D3: T-2026-0002 | E3: Rechnung | G3: Jonas Becker | H3: DE | I3: 177.64 | J3: 0.19 | K3: 33.75 | L3: 211.39 | M3: [{"text":"PSA 10 Gengar (japanisch) (yahoo, 1 Stk.)","sub":"Beschaffung in Japan inkl. Import · Sendico-Nr. Z-160889","net":177.64}]
A4: RE-2026-0003 | B4: 46289.552 | C4: 46289.552 | D4: T-2026-0003 | E4: Rechnung | G4: Mia Wagner | H4: AT | I4: 90.46 | J4: 0.19 | K4: 17.19 | L4: 107.65 | M4: [{"text":"One Piece Card Game Booster Display (surugaya, 1 Stk.)","sub":"Beschaffung in Japan inkl. Import · Sendico-Nr. Z-160404","net":64.64},{"text":"Yu-Gi-Oh! OCG Booster (3 Packs) (mercari, 1 Stk.)","sub":"Beschaffung in Japan inkl. Import · Sendico-Nr. Z-162161","net":25.82}]

Sheet Journal
A1: BU_Nr | B1: BU_Datum | C1: BU_Beleg | D1: BU_Text | E1: BU_Soll | F1: BU_Haben | G1: BU_Betrag | H1: BU_Steuer | I1: BU_Steuerbetrag | J1: BU_Bezug
A2: 1 | B2: 46277.677 | C2: T-2026-0003 | D2: Überweisung T-2026-0003 Mia Wagner | E2: 1200 | F2: 1718 | G2: 107.65 | H2: USt 19 % (Anzahlung) | I2: 17.19 | J2: T-2026-0003
A3: 2 | B3: 46273.76 | C3: T-2026-0001-1 | D3: Wareneinkauf Japan mercari Z-165243 | E3: 3200 | F3: 1210 | G3: 50 | I3: 0 | J3: T-2026-0001-1
A4: 3 | B4: 46273.76 | C4: T-2026-0001-1 | D4: Sendico-Gebühr Z-165243 | E4: 3800 | F4: 1210 | G4: 4.32 | H4: §13b (Leistung aus Drittland – prüfen) | I4: 0 | J4: T-2026-0001-1
A5: 4 | B5: 46273.76 | C5: T-2026-0001-2 | D5: Wareneinkauf Japan mercari Z-162253 | E5: 3200 | F5: 1210 | G5: 22.7 | I5: 0 | J5: T-2026-0001-2
A6: 5 | B6: 46273.76 | C6: T-2026-0001-2 | D6: Sendico-Gebühr Z-162253 | E6: 3800 | F6: 1210 | G6: 4.32 | H6: §13b (Leistung aus Drittland – prüfen) | I6: 0 | J6: T-2026-0001-2
A7: 6 | B7: 46273.76 | C7: T-2026-0001 | D7: Zahlung paypal T-2026-0001 Lena Hoffmann | E7: 1360 | F7: 1718 | G7: 123.45 | H7: USt 19 % (Anzahlung) | I7: 19.71 | J7: T-2026-0001
A8: 7 | B8: 46273.76 | C8: T-2026-0001 | D8: Zahlungsgebühr paypal (Schätzung, Ist laut Abrechnung) | E8: 4970 | F8: 1360 | G8: 3.42 | I8: 0 | J8: T-2026-0001
A9: 8 | B9: 46275.76 | C9: T-2026-0002-1 | D9: Wareneinkauf Japan yahoo Z-160889 | E9: 3200 | F9: 1210 | G9: 144.86 | I9: 0 | J9: T-2026-0002-1
A10: 9 | B10: 46275.76 | C10: T-2026-0002-1 | D10: Sendico-Gebühr Z-160889 | E10: 3800 | F10: 1210 | G10: 4.32 | H10: §13b (Leistung aus Drittland – prüfen) | I10: 0 | J10: T-2026-0002-1
A11: 10 | B11: 46275.76 | C11: T-2026-0002 | D11: Zahlung stripe T-2026-0002 Jonas Becker | E11: 1360 | F11: 1718 | G11: 211.39 | H11: USt 19 % (Anzahlung) | I11: 33.75 | J11: T-2026-0002
A12: 11 | B12: 46275.76 | C12: T-2026-0002 | D12: Zahlungsgebühr stripe (Schätzung, Ist laut Abrechnung) | E12: 4970 | F12: 1360 | G12: 5.61 | I12: 0 | J12: T-2026-0002
A13: 12 | B13: 46277.76 | C13: T-2026-0003-1 | D13: Wareneinkauf Japan surugaya Z-160404 | E13: 3200 | F13: 1210 | G13: 37.3 | I13: 0 | J13: T-2026-0003-1
A14: 13 | B14: 46277.76 | C14: T-2026-0003-1 | D14: Sendico-Gebühr Z-160404 | E14: 3800 | F14: 1210 | G14: 2.7 | H14: §13b (Leistung aus Drittland – prüfen) | I14: 0 | J14: T-2026-0003-1
A15: 14 | B15: 46277.76 | C15: T-2026-0003-2 | D15: Wareneinkauf Japan mercari Z-162161 | E15: 3200 | F15: 1210 | G15: 12.97 | I15: 0 | J15: T-2026-0003-2
A16: 15 | B16: 46277.76 | C16: T-2026-0003-2 | D16: Sendico-Gebühr Z-162161 | E16: 3800 | F16: 1210 | G16: 4.32 | H16: §13b (Leistung aus Drittland – prüfen) | I16: 0 | J16: T-2026-0003-2
A17: 16 | B17: 46282.302 | C17: S-2026-09-1 | D17: Fracht Sammelsendung S-2026-09-1 (Sendico) | E17: 3800 | F17: 1210 | G17: 26.49 | I17: 0 | J17: S-2026-09-1
A18: 17 | B18: 46288.385 | C18: S-2026-09-1 | D18: Zoll S-2026-09-1 | E18: 3850 | F18: 1200 | G18: 4.1 | I18: 0 | J18: S-2026-09-1
A19: 18 | B19: 46288.385 | C19: S-2026-09-1 | D19: Einfuhrumsatzsteuer S-2026-09-1 | E19: 1588 | F19: 1200 | G19: 63.4 | H19: EUSt (Vorsteuer) | I19: 63.4 | J19: S-2026-09-1
A20: 19 | B20: 46288.385 | C20: S-2026-09-1 | D20: Verzollungsgebühr Kurier S-2026-09-1 | E20: 3800 | F20: 1200 | G20: 15 | I20: 0 | J20: S-2026-09-1
A21: 20 | B21: 46289.552 | C21: RE-2026-0001 | D21: Rechnung RE-2026-0001 Lena Hoffmann – Auflösung Anzahlung | E21: 1718 | F21: 8400 | G21: 123.45 | H21: USt 19 % (bereits mit Anzahlung erfasst) | I21: 0 | J21: T-2026-0001
A22: 21 | B22: 46289.552 | C22: RE-2026-0001 | D22: Porto an Kunden T-2026-0001 | E22: 4910 | F22: 1200 | G22: 6.19 | I22: 0 | J22: T-2026-0001
A23: 22 | B23: 46289.552 | C23: RE-2026-0002 | D23: Rechnung RE-2026-0002 Jonas Becker – Auflösung Anzahlung | E23: 1718 | F23: 8400 | G23: 211.39 | H23: USt 19 % (bereits mit Anzahlung erfasst) | I23: 0 | J23: T-2026-0002
A24: 23 | B24: 46289.552 | C24: RE-2026-0002 | D24: Porto an Kunden T-2026-0002 | E24: 4910 | F24: 1200 | G24: 6.19 | I24: 0 | J24: T-2026-0002
A25: 24 | B25: 46289.552 | C25: RE-2026-0003 | D25: Rechnung RE-2026-0003 Mia Wagner – Auflösung Anzahlung | E25: 1718 | F25: 8400 | G25: 107.65 | H25: USt 19 % (bereits mit Anzahlung erfasst) | I25: 0 | J25: T-2026-0003
A26: 25 | B26: 46289.552 | C26: RE-2026-0003 | D26: Porto an Kunden T-2026-0003 | E26: 4910 | F26: 1200 | G26: 14.9 | I26: 0 | J26: T-2026-0003
A27: 26 | B27: 46304.76 | C27: T-2026-0004-1 | D27: Wareneinkauf Japan mercari Z-165893 | E27: 3200 | F27: 1210 | G27: 85.41 | I27: 0 | J27: T-2026-0004-1
A28: 27 | B28: 46304.76 | C28: T-2026-0004-1 | D28: Sendico-Gebühr Z-165893 | E28: 3800 | F28: 1210 | G28: 4.32 | H28: §13b (Leistung aus Drittland – prüfen) | I28: 0 | J28: T-2026-0004-1
A29: 28 | B29: 46304.76 | C29: T-2026-0004-2 | D29: Wareneinkauf Japan mercari Z-161163 | E29: 3200 | F29: 1210 | G29: 18.92 | I29: 0 | J29: T-2026-0004-2
A30: 29 | B30: 46304.76 | C30: T-2026-0004-2 | D30: Sendico-Gebühr Z-161163 | E30: 3800 | F30: 1210 | G30: 4.32 | H30: §13b (Leistung aus Drittland – prüfen) | I30: 0 | J30: T-2026-0004-2
A31: 30 | B31: 46304.76 | C31: T-2026-0004 | D31: Zahlung paypal T-2026-0004 Tim Schulz | E31: 1360 | F31: 1718 | G31: 164.79 | H31: USt 19 % (Anzahlung) | I31: 26.31 | J31: T-2026-0004
A32: 31 | B32: 46304.76 | C32: T-2026-0004 | D32: Zahlungsgebühr paypal (Schätzung, Ist laut Abrechnung) | E32: 4970 | F32: 1360 | G32: 4.45 | I32: 0 | J32: T-2026-0004
A33: 32 | B33: 46308.76 | C33: T-2026-0005-1 | D33: Wareneinkauf Japan mercari Z-160845 | E33: 3200 | F33: 1210 | G33: 40 | I33: 0 | J33: T-2026-0005-1
A34: 33 | B34: 46308.76 | C34: T-2026-0005-1 | D34: Sendico-Gebühr Z-160845 | E34: 3800 | F34: 1210 | G34: 4.32 | H34: §13b (Leistung aus Drittland – prüfen) | I34: 0 | J34: T-2026-0005-1
A35: 34 | B35: 46308.76 | C35: T-2026-0005 | D35: Zahlung stripe T-2026-0005 Sara Klein | E35: 1360 | F35: 1718 | G35: 67.93 | H35: USt 19 % (Anzahlung) | I35: 10.85 | J35: T-2026-0005
A36: 35 | B36: 46308.76 | C36: T-2026-0005 | D36: Zahlungsgebühr stripe (Schätzung, Ist laut Abrechnung) | E36: 4970 | F36: 1360 | G36: 2.04 | I36: 0 | J36: T-2026-0005

Sheet Postausgang
A1: PA_Nr | B1: PA_Datum | C1: PA_An | D1: PA_Betreff | E1: PA_Bestellung | F1: PA_Text
A2: 1 | B2: 46272.302 | C2: lena@example.de | D2: Deine Bestellung ist eingegangen (T-2026-0001) | E2: T-2026-0001 | F2: <div style="font-family:Arial,sans-serif;max-width:560px;color:#17171A;line-height:1.55"> <p style="font-weight:900;font-size:18px;margin:0 0 18px"><span style="border:2px solid #B4341C;color:#B4341C;border-radius:5px;padding:0 5px;margin-right:6px">積</span>Tsumiki</p> <h2 style="font-size:20px;margin:0 0 12px">Deine Bestellung ist eingegangen</h2><p>Hallo Lena Hoffmann,</p><p>danke für deine Bestellung <strong>T-2026-0001</strong>. Wir kaufen deine Artikel in den nächsten Stunden in Japan. Den Betrag von <strong>123,45 €</strong> haben wir nur vorgemerkt – abgebucht wird erst, wenn unser Kauf geklappt hat.</p><ul><li>Pikachu Promo (japanisch) – 82,07 €</li><li>Evoli Illustration Rare – 41,38 €</li></ul> <p style="margin:22px 0"><a href="http://localhost:3000/status.html?b=y4ertga730uyvix4" style="background:#B4341C;color:#fff;text-decoration:none;padding:12px 18px;border-radius:8px;font-weight:bold">Bestellung ansehen</a></p> <p style="color:#5C5C63;font-size:13px;margin-top:28px">Tsumiki · Bastian Karlshaus · [PLZ] Wuppertal</p></div>
A3: 2 | B3: 46274.302 | C3: jonas@example.de | D3: Deine Bestellung ist eingegangen (T-2026-0002) | E3: T-2026-0002 | F3: <div style="font-family:Arial,sans-serif;max-width:560px;color:#17171A;line-height:1.55"> <p style="font-weight:900;font-size:18px;margin:0 0 18px"><span style="border:2px solid #B4341C;color:#B4341C;border-radius:5px;padding:0 5px;margin-right:6px">積</span>Tsumiki</p> <h2 style="font-size:20px;margin:0 0 12px">Deine Bestellung ist eingegangen</h2><p>Hallo Jonas Becker,</p><p>danke für deine Bestellung <strong>T-2026-0002</strong>. Wir kaufen deine Artikel in den nächsten Stunden in Japan. Den Betrag von <strong>211,39 €</strong> haben wir nur vorgemerkt – abgebucht wird erst, wenn unser Kauf geklappt hat.</p><ul><li>PSA 10 Gengar (japanisch) – 211,39 €</li></ul> <p style="margin:22px 0"><a href="http://localhost:3000/status.html?b=v3wzgijaoivp7mnb" style="background:#B4341C;color:#fff;text-decoration:none;padding:12px 18px;border-radius:8px;font-weight:bold">Bestellung ansehen</a></p> <p style="color:#5C5C63;font-size:13px;margin-top:28px">Tsumiki · Bastian Karlshaus · [PLZ] Wuppertal</p></div>
A4: 3 | B4: 46276.302 | C4: mia@example.de | D4: Bitte überweise den Betrag (T-2026-0003) | E4: T-2026-0003 | F4: <div style="font-family:Arial,sans-serif;max-width:560px;color:#17171A;line-height:1.55"> <p style="font-weight:900;font-size:18px;margin:0 0 18px"><span style="border:2px solid #B4341C;color:#B4341C;border-radius:5px;padding:0 5px;margin-right:6px">積</span>Tsumiki</p> <h2 style="font-size:20px;margin:0 0 12px">Bitte überweise den Betrag</h2><p>Hallo Mia Wagner,</p><p>bitte überweise <strong>107,65 €</strong> an:<br>Bastian Karlshaus<br>IBAN DE00 0000 0000 0000 0000 00<br>Verwendungszweck: <strong>T-2026-0003</strong></p><p>Sobald das Geld da ist, kaufen wir für dich ein. Ist ein Artikel bis dahin weg, erstatten wir den Betrag sofort.</p> <p style="margin:22px 0"><a href="http://localhost:3000/status.html?b=ncs9rl8kdnmubgr1" style="background:#B4341C;color:#fff;text-decoration:none;padding:12px 18px;border-radius:8px;font-weight:bold">Bestellung ansehen</a></p> <p style="color:#5C5C63;font-size:13px;margin-top:28px">Tsumiki · Bastian Karlshaus · [PLZ] Wuppertal</p></div>
A5: 4 | B5: 46303.302 | C5: tim@example.de | D5: Deine Bestellung ist eingegangen (T-2026-0004) | E5: T-2026-0004 | F5: <div style="font-family:Arial,sans-serif;max-width:560px;color:#17171A;line-height:1.55"> <p style="font-weight:900;font-size:18px;margin:0 0 18px"><span style="border:2px solid #B4341C;color:#B4341C;border-radius:5px;padding:0 5px;margin-right:6px">積</span>Tsumiki</p> <h2 style="font-size:20px;margin:0 0 12px">Deine Bestellung ist eingegangen</h2><p>Hallo Tim Schulz,</p><p>danke für deine Bestellung <strong>T-2026-0004</strong>. Wir kaufen deine Artikel in den nächsten Stunden in Japan. Den Betrag von <strong>191,39 €</strong> haben wir nur vorgemerkt – abgebucht wird erst, wenn unser Kauf geklappt hat.</p><ul><li>Glurak SAR (japanisch) – 128,22 €</li><li>Mew Promo (japanisch) – 34,26 €</li><li>Relaxo Art Rare – 28,91 €</li></ul> <p style="margin:22px 0"><a href="http://localhost:3000/status.html?b=e0n1di8agv9gy13z" style="background:#B4341C;color:#fff;text-decoration:none;padding:12px 18px;border-radius:8px;font-weight:bold">Bestellung ansehen</a></p> <p style="color:#5C5C63;font-size:13px;margin-top:28px">Tsumiki · Bastian Karlshaus · [PLZ] Wuppertal</p></div>
A6: 5 | B6: 46307.302 | C6: sara@example.de | D6: Deine Bestellung ist eingegangen (T-2026-0005) | E6: T-2026-0005 | F6: <div style="font-family:Arial,sans-serif;max-width:560px;color:#17171A;line-height:1.55"> <p style="font-weight:900;font-size:18px;margin:0 0 18px"><span style="border:2px solid #B4341C;color:#B4341C;border-radius:5px;padding:0 5px;margin-right:6px">積</span>Tsumiki</p> <h2 style="font-size:20px;margin:0 0 12px">Deine Bestellung ist eingegangen</h2><p>Hallo Sara Klein,</p><p>danke für deine Bestellung <strong>T-2026-0005</strong>. Wir kaufen deine Artikel in den nächsten Stunden in Japan. Den Betrag von <strong>67,93 €</strong> haben wir nur vorgemerkt – abgebucht wird erst, wenn unser Kauf geklappt hat.</p><ul><li>Nachtara Alt Art (japanisch) – 67,93 €</li></ul> <p style="margin:22px 0"><a href="http://localhost:3000/status.html?b=79dtwjhbzn3cvmk2" style="background:#B4341C;color:#fff;text-decoration:none;padding:12px 18px;border-radius:8px;font-weight:bold">Bestellung ansehen</a></p> <p style="color:#5C5C63;font-size:13px;margin-top:28px">Tsumiki · Bastian Karlshaus · [PLZ] Wuppertal</p></div>
A7: 6 | B7: 46312.302 | C7: paul@example.de | D7: Deine Bestellung ist eingegangen (T-2026-0006) | E7: T-2026-0006 | F7: <div style="font-family:Arial,sans-serif;max-width:560px;color:#17171A;line-height:1.55"> <p style="font-weight:900;font-size:18px;margin:0 0 18px"><span style="border:2px solid #B4341C;color:#B4341C;border-radius:5px;padding:0 5px;margin-right:6px">積</span>Tsumiki</p> <h2 style="font-size:20px;margin:0 0 12px">Deine Bestellung ist eingegangen</h2><p>Hallo Paul Neumann,</p><p>danke für deine Bestellung <strong>T-2026-0006</strong>. Wir kaufen deine Artikel in den nächsten Stunden in Japan. Den Betrag von <strong>119,40 €</strong> haben wir nur vorgemerkt – abgebucht wird erst, wenn unser Kauf geklappt hat.</p><ul><li>PSA 10 Bisasam (japanisch) – 99,27 €</li><li>Digimon Card Game Promo – 20,13 €</li></ul> <p style="margin:22px 0"><a href="http://localhost:3000/status.html?b=t5ezyohtuy035kzw" style="background:#B4341C;color:#fff;text-decoration:none;padding:12px 18px;border-radius:8px;font-weight:bold">Bestellung ansehen</a></p> <p style="color:#5C5C63;font-size:13px;margin-top:28px">Tsumiki · Bastian Karlshaus · [PLZ] Wuppertal</p></div>
A8: 7 | B8: 46273.76 | C8: lena@example.de | D8: Gekauft! Deine Artikel liegen in Japan bereit (T-2026-0001) | E8: T-2026-0001 | F8: <div style="font-family:Arial,sans-serif;max-width:560px;color:#17171A;line-height:1.55"> <p style="font-weight:900;font-size:18px;margin:0 0 18px"><span style="border:2px solid #B4341C;color:#B4341C;border-radius:5px;padding:0 5px;margin-right:6px">積</span>Tsumiki</p> <h2 style="font-size:20px;margin:0 0 12px">Gekauft! Deine Artikel liegen in Japan bereit</h2><p>Hallo Lena Hoffmann,</p><p>wir haben für dich gekauft. Abgebucht wurden <strong>123,45 €</strong>.</p><ul><li>Pikachu Promo (japanisch) – 82,07 €</li><li>Evoli Illustration Rare – 41,38 €</li></ul><p>Deine Artikel kommen mit der nächsten Sammelsendung (Stichtag 20. September 2026).</p> <p style="margin:22px 0"><a href="http://localhost:3000/status.html?b=y4ertga730uyvix4" style="background:#B4341C;color:#fff;text-decoration:none;padding:12px 18px;border-radius:8px;font-weight:bold">Bestellung ansehen</a></p> <p style="color:#5C5C63;font-size:13px;margin-top:28px">Tsumiki · Bastian Karlshaus · [PLZ] Wuppertal</p></div>
A9: 8 | B9: 46275.76 | C9: jonas@example.de | D9: Gekauft! Deine Artikel liegen in Japan bereit (T-2026-0002) | E9: T-2026-0002 | F9: <div style="font-family:Arial,sans-serif;max-width:560px;color:#17171A;line-height:1.55"> <p style="font-weight:900;font-size:18px;margin:0 0 18px"><span style="border:2px solid #B4341C;color:#B4341C;border-radius:5px;padding:0 5px;margin-right:6px">積</span>Tsumiki</p> <h2 style="font-size:20px;margin:0 0 12px">Gekauft! Deine Artikel liegen in Japan bereit</h2><p>Hallo Jonas Becker,</p><p>wir haben für dich gekauft. Abgebucht wurden <strong>211,39 €</strong>.</p><ul><li>PSA 10 Gengar (japanisch) – 211,39 €</li></ul><p>Deine Artikel kommen mit der nächsten Sammelsendung (Stichtag 20. September 2026).</p> <p style="margin:22px 0"><a href="http://localhost:3000/status.html?b=v3wzgijaoivp7mnb" style="background:#B4341C;color:#fff;text-decoration:none;padding:12px 18px;border-radius:8px;font-weight:bold">Bestellung ansehen</a></p> <p style="color:#5C5C63;font-size:13px;margin-top:28px">Tsumiki · Bastian Karlshaus · [PLZ] Wuppertal</p></div>
A10: 9 | B10: 46277.76 | C10: mia@example.de | D10: Gekauft! Deine Artikel liegen in Japan bereit (T-2026-0003) | E10: T-2026-0003 | F10: <div style="font-family:Arial,sans-serif;max-width:560px;color:#17171A;line-height:1.55"> <p style="font-weight:900;font-size:18px;margin:0 0 18px"><span style="border:2px solid #B4341C;color:#B4341C;border-radius:5px;padding:0 5px;margin-right:6px">積</span>Tsumiki</p> <h2 style="font-size:20px;margin:0 0 12px">Gekauft! Deine Artikel liegen in Japan bereit</h2><p>Hallo Mia Wagner,</p><p>wir haben für dich gekauft. Abgebucht wurden <strong>107,65 €</strong>.</p><ul><li>One Piece Card Game Booster Display – 76,92 €</li><li>Yu-Gi-Oh! OCG Booster (3 Packs) – 30,73 €</li></ul><p>Deine Artikel kommen mit der nächsten Sammelsendung (Stichtag 20. September 2026).</p> <p style="margin:22px 0"><a href="http://localhost:3000/status.html?b=ncs9rl8kdnmubgr1" style="background:#B4341C;color:#fff;text-decoration:none;padding:12px 18px;border-radius:8px;font-weight:bold">Bestellung ansehen</a></p> <p style="color:#5C5C63;font-size:13px;margin-top:28px">Tsumiki · Bastian Karlshaus · [PLZ] Wuppertal</p></div>
A11: 10 | B11: 46282.302 | C11: lena@example.de | D11: Deine Sammelsendung ist unterwegs (T-2026-0001) | E11: T-2026-0001 | F11: <div style="font-family:Arial,sans-serif;max-width:560px;color:#17171A;line-height:1.55"> <p style="font-weight:900;font-size:18px;margin:0 0 18px"><span style="border:2px solid #B4341C;color:#B4341C;border-radius:5px;padding:0 5px;margin-right:6px">積</span>Tsumiki</p> <h2 style="font-size:20px;margin:0 0 12px">Deine Sammelsendung ist unterwegs</h2><p>Hallo Lena Hoffmann,</p><p>die Kiste mit deinen Artikeln hat Japan verlassen. In etwa einer Woche ist sie in Wuppertal, dann packen wir sofort für dich.</p> <p style="margin:22px 0"><a href="http://localhost:3000/status.html?b=y4ertga730uyvix4" style="background:#B4341C;color:#fff;text-decoration:none;padding:12px 18px;border-radius:8px;font-weight:bold">Bestellung ansehen</a></p> <p style="color:#5C5C63;font-size:13px;margin-top:28px">Tsumiki · Bastian Karlshaus · [PLZ] Wuppertal</p></div>
A12: 11 | B12: 46282.302 | C12: jonas@example.de | D12: Deine Sammelsendung ist unterwegs (T-2026-0002) | E12: T-2026-0002 | F12: <div style="font-family:Arial,sans-serif;max-width:560px;color:#17171A;line-height:1.55"> <p style="font-weight:900;font-size:18px;margin:0 0 18px"><span style="border:2px solid #B4341C;color:#B4341C;border-radius:5px;padding:0 5px;margin-right:6px">積</span>Tsumiki</p> <h2 style="font-size:20px;margin:0 0 12px">Deine Sammelsendung ist unterwegs</h2><p>Hallo Jonas Becker,</p><p>die Kiste mit deinen Artikeln hat Japan verlassen. In etwa einer Woche ist sie in Wuppertal, dann packen wir sofort für dich.</p> <p style="margin:22px 0"><a href="http://localhost:3000/status.html?b=v3wzgijaoivp7mnb" style="background:#B4341C;color:#fff;text-decoration:none;padding:12px 18px;border-radius:8px;font-weight:bold">Bestellung ansehen</a></p> <p style="color:#5C5C63;font-size:13px;margin-top:28px">Tsumiki · Bastian Karlshaus · [PLZ] Wuppertal</p></div>
A13: 12 | B13: 46282.302 | C13: mia@example.de | D13: Deine Sammelsendung ist unterwegs (T-2026-0003) | E13: T-2026-0003 | F13: <div style="font-family:Arial,sans-serif;max-width:560px;color:#17171A;line-height:1.55"> <p style="font-weight:900;font-size:18px;margin:0 0 18px"><span style="border:2px solid #B4341C;color:#B4341C;border-radius:5px;padding:0 5px;margin-right:6px">積</span>Tsumiki</p> <h2 style="font-size:20px;margin:0 0 12px">Deine Sammelsendung ist unterwegs</h2><p>Hallo Mia Wagner,</p><p>die Kiste mit deinen Artikeln hat Japan verlassen. In etwa einer Woche ist sie in Wuppertal, dann packen wir sofort für dich.</p> <p style="margin:22px 0"><a href="http://localhost:3000/status.html?b=ncs9rl8kdnmubgr1" style="background:#B4341C;color:#fff;text-decoration:none;padding:12px 18px;border-radius:8px;font-weight:bold">Bestellung ansehen</a></p> <p style="color:#5C5C63;font-size:13px;margin-top:28px">Tsumiki · Bastian Karlshaus · [PLZ] Wuppertal</p></div>
... A18: 17 | B18: 46308.76 | C18: sara@example.de | D18: Gekauft! Deine Artikel liegen in Japan bereit (T-2026-0005) | E18: T-2026-0005 | F18: <div style="font-family:Arial,sans-serif;max-width:560px;color:#17171A;line-height:1.55"> <p style="font-weight:900;font-size:18px;margin:0 0 18px"><span style="border:2px solid #B4341C;color:#B4341C;border-radius:5px;padding:0 5px;margin-right:6px">積</span>Tsumiki</p> <h2 style="font-size:20px;margin:0 0 12px">Gekauft! Deine Artikel liegen in Japan bereit</h2><p>Hallo Sara Klein,</p><p>wir haben für dich gekauft. Abgebucht wurden <strong>67,93 €</strong>.</p><ul><li>Nachtara Alt Art (japanisch) – 67,93 €</li></ul><p>Deine Artikel kommen mit der nächsten Sammelsendung (Stichtag 20. Oktober 2026).</p> <p style="margin:22px 0"><a href="http://localhost:3000/status.html?b=79dtwjhbzn3cvmk2" style="background:#B4341C;color:#fff;text-decoration:none;padding:12px 18px;border-radius:8px;font-weight:bold">Bestellung ansehen</a></p> <p style="color:#5C5C63;font-size:13px;margin-top:28px">Tsumiki · Bastian Karlshaus · [PLZ] Wuppertal</p></div>

Sheet Protokoll
A1: LOG_Datum | B1: LOG_Aktion | C1: LOG_Bezug | D1: LOG_Details
A2: 46272.302 | B2: Bestellung angelegt | C2: T-2026-0001 | D2: {"gross":123.45,"items":2,"pay":"paypal"}
A3: 46272.302 | B3: Zahlung reserviert | C3: T-2026-0001 | D3: {"ref":"DEMO-T-2026-0001","amount":123.45}
A4: 46274.302 | B4: Bestellung angelegt | C4: T-2026-0002 | D4: {"gross":211.39,"items":1,"pay":"stripe"}
A5: 46274.302 | B5: Zahlung reserviert | C5: T-2026-0002 | D5: {"ref":"DEMO-T-2026-0002","amount":211.39}
A6: 46276.302 | B6: Bestellung angelegt | C6: T-2026-0003 | D6: {"gross":107.65,"items":2,"pay":"ueberweisung"}
A7: 46277.677 | B7: Überweisung eingegangen | C7: T-2026-0003 | D7: 107.65
A8: 46303.302 | B8: Bestellung angelegt | C8: T-2026-0004 | D8: {"gross":191.39,"items":3,"pay":"paypal"}
A9: 46303.302 | B9: Zahlung reserviert | C9: T-2026-0004 | D9: {"ref":"DEMO-T-2026-0004","amount":191.39}
A10: 46307.302 | B10: Bestellung angelegt | C10: T-2026-0005 | D10: {"gross":67.93,"items":1,"pay":"stripe"}
A11: 46307.302 | B11: Zahlung reserviert | C11: T-2026-0005 | D11: {"ref":"DEMO-T-2026-0005","amount":67.93}
A12: 46312.302 | B12: Bestellung angelegt | C12: T-2026-0006 | D12: {"gross":119.4,"items":2,"pay":"paypal"}
A13: 46312.302 | B13: Zahlung reserviert | C13: T-2026-0006 | D13: {"ref":"DEMO-T-2026-0006","amount":119.4}
... A26: 46304.76 | B26: Gekauft | C26: T-2026-0004-2 | D26: {"sendicoNo":"Z-161163","jpy":3500}
A27: 46304.76 | B27: Nicht verfügbar | C27: T-2026-0004-3
A28: 46308.76 | B28: Gekauft | C28: T-2026-0005-1 | D28: {"sendicoNo":"Z-160845","jpy":7400}

Sheet Auswertung
A1: Auswertung
A3: Bestellungen gesamt | B3: =COUNTA(Bestellungen!A:A)-1
A4: … warten auf Kauf (Status "neu") | B4: =COUNTIF(Bestellungen!D:D,"neu")
A5: … warten auf Überweisung | B5: =COUNTIF(Bestellungen!D:D,"zahlung_offen")
A6: … im Lager Japan (gekauft) | B6: =COUNTIF(Bestellungen!D:D,"gekauft")
A7: … unterwegs | B7: =COUNTIF(Bestellungen!D:D,"unterwegs")
A8: … angekommen, zu versenden | B8: =COUNTIF(Bestellungen!D:D,"angekommen")
A9: … versendet | B9: =COUNTIF(Bestellungen!D:D,"versendet")
A10: Abgebuchter Umsatz brutto | B10: =SUM(Bestellungen!O:O)
A11: Servicegebühren (netto, kalkuliert) | B11: =SUMIF(Bestellungen!O:O,">0",Bestellungen!R:R)
A12: Logistik kalkuliert (alle Sendungen) | B12: =SUM(Sammelsendungen!P:P)
A13: Logistik tatsächlich | B13: =SUM(Sammelsendungen!Q:Q)
A14: Abweichung (positiv = günstiger als kalkuliert) | B14: =SUM(Sammelsendungen!R:R)
A15: Rechnungen ausgestellt | B15: =COUNTIF(Rechnungen!E:E,"Rechnung")
A16: Gutschriften | B16: =COUNTIF(Rechnungen!E:E,"Gutschrift")
A19: Umsatzsteuer, Ergebnis je Auftrag und Nachkalkulation: in der Verwaltung unter „Buchhaltung“.
